sanic_useragent/__init__.py
sanic_useragent-0.1.4.dist-info/METADATA
sanic_useragent-0.1.4.dist-info/WHEEL
sanic_useragent-0.1.4.dist-info/top_level.txt
sanic_useragent-0.1.4.dist-info/RECORD
